{
  "TeamMentor_Article": {
    "$": {
      "Metadata_Hash": "-40857053",
      "Content_Hash": "2046686358"
    },
    "Metadata": [
      {
        "Id": [
          "00000000-0000-0000-0000-00000087e538"
        ],
        "Library_Id": [
          "eb39d862-f752-4d1c-ab6e-14ed697397c0"
        ],
        "Title": [
          "Filters Pane"
        ],
        "Category": [
          "User Interface"
        ],
        "Phase": [
          "NA"
        ],
        "Technology": [
          "TEAM Mentor"
        ],
        "Type": [
          "Documentation"
        ],
        "DirectLink": [
          ""
        ],
        "Tag": [
          ""
        ],
        "Security_Demand": [
          ""
        ],
        "Author": [
          ""
        ],
        "Priority": [
          ""
        ],
        "Status": [
          ""
        ]
      }
    ],
    "Content": [
      {
        "$": {
          "Sanitized": "true",
          "DataType": "Html"
        },
        "Data": [
          "The filters pane allows filtering content in the current library/folder/view based on applicable technology, development phase, article type, and subject matter category. Filters can be enabled or disabled by using the corresponding checkboxes."
        ]
      }
    ]
  }
}