{
  "id": "00000000-0000-0000-0000-00000060a93a",
  "checksum": "fa51718543fcb8446c09d466a8450474860109bc",
  "words": {
    "here": [
      "font"
    ],
    "are": [
      "font"
    ],
    "a": [
      "font"
    ],
    "number": [
      "font"
    ],
    "of": [
      "font"
    ],
    "useful": [
      "font"
    ],
    "git": [
      "font",
      "div",
      "ul",
      "li",
      "font",
      "title"
    ],
    "scripts": [
      "font",
      "title"
    ],
    "update": [
      "div"
    ],
    "an": [
      "div"
    ],
    "repository": [
      "div"
    ],
    "with": [
      "div"
    ],
    "the": [
      "div"
    ],
    "latest": [
      "div"
    ],
    "changes": [
      "div"
    ],
    "$git": [
      "div",
      "ul",
      "li",
      "font"
    ],
    "pull": [
      "div",
      "ul",
      "li",
      "font"
    ],
    "origin\n\n\n\nreferences\n\n\ngit": [
      "div"
    ],
    "stash": [
      "div",
      "div",
      "ul",
      "li",
      "font"
    ],
    "http//book.git-scm.com/4_stashing.html": [
      "div",
      "div",
      "ul",
      "li",
      "a"
    ],
    "origin": [
      "ul",
      "li",
      "font"
    ],
    "references": [
      "div",
      "font"
    ]
  },
  "tags": {
    "font": [
      "Here are a number of useful Git Scripts",
      "$git pull origin",
      "",
      "References",
      "Git Stash:"
    ],
    "div": [
      "",
      "Update an repository with the latest changes",
      "$git pull origin\n\n\n\n\nReferences\n\n\nGit Stash:  \nhttp://book.git-scm.com/4_stashing.html",
      "",
      "References",
      "Git Stash:  \nhttp://book.git-scm.com/4_stashing.html"
    ],
    "br": [
      "",
      ""
    ],
    "ul": [
      "$git pull origin",
      "Git Stash:  \nhttp://book.git-scm.com/4_stashing.html"
    ],
    "li": [
      "$git pull origin",
      "Git Stash:  \nhttp://book.git-scm.com/4_stashing.html"
    ],
    "a": [
      "http://book.git-scm.com/4_stashing.html"
    ]
  },
  "links": [
    {
      "href": "http://book.git-scm.com/4_stashing.html",
      "text": "\nhttp://book.git-scm.com/4_stashing.html"
    }
  ],
  "html": "<font face=\"Arial, Verdana\" size=\"2\" style=\"font-family:Arial,Verdana; font-style:normal; font-variant:normal; font-weight:normal; line-height:normal; font-size:10pt\">Here are a number of useful Git Scripts</font>\n<div style=\"font-family:Arial,Verdana; font-size:10pt; font-style:normal; font-variant:normal; font-weight:normal; line-height:normal\">\n<br>\n</div>\n<div style=\"font-family:Arial,Verdana; font-size:10pt; font-style:normal; font-variant:normal; font-weight:normal; line-height:normal\">\nUpdate an repository with the latest changes</div>\n<div>\n<ul style=\"font-family:Arial,Verdana; font-style:normal; font-variant:normal; font-weight:normal; line-height:normal; font-size:10pt\">\n<li><font face=\"Arial, Verdana\" size=\"2\">$git pull origin</font></li></ul>\n<div style=\"font-family:Arial,Verdana; font-style:normal; font-variant:normal; font-weight:normal; line-height:normal\">\n<font size=\"2\"><br>\n</font></div>\n<div style=\"font-family:Arial,Verdana; font-style:normal; font-variant:normal; font-weight:normal; line-height:normal\">\n<font size=\"2\">References</font></div>\n<div>\n<ul>\n<li><font face=\"Arial, Verdana\" size=\"2\">Git Stash:&nbsp;</font> <a href=\"http://book.git-scm.com/4_stashing.html\">\nhttp://book.git-scm.com/4_stashing.html</a></li></ul>\n</div>\n</div>\n"
}