{
  "id": "00000000-0000-0000-0000-000000579bb9",
  "checksum": "c1a35022cd1bbd92f4de5a0311e958e7",
  "words": {
    "editing": [
      "div",
      "title"
    ],
    "content": [
      "div",
      "div",
      "div"
    ],
    "in": [
      "div",
      "div",
      "div",
      "div"
    ],
    "team": [
      "div",
      "div"
    ],
    "mentor": [
      "div",
      "div"
    ],
    "is": [
      "div",
      "div"
    ],
    "done": [
      "div"
    ],
    "via": [
      "div",
      "div",
      "div"
    ],
    "edit": [
      "div",
      "div",
      "div",
      "div",
      "div",
      "div",
      "div"
    ],
    "mode": [
      "div",
      "div",
      "div",
      "div",
      "div",
      "div",
      "div"
    ],
    "only": [
      "div"
    ],
    "available": [
      "div"
    ],
    "to": [
      "div",
      "div",
      "div",
      "div",
      "div"
    ],
    "editors": [
      "div"
    ],
    "and": [
      "div",
      "div",
      "div",
      "div"
    ],
    "administrators": [
      "div"
    ],
    "access": [
      "div"
    ],
    "login": [
      "div"
    ],
    "as": [
      "div"
    ],
    "either": [
      "div"
    ],
    "an": [
      "div",
      "div"
    ],
    "administrator": [
      "div"
    ],
    "or": [
      "div"
    ],
    "editor": [
      "div"
    ],
    "user": [
      "div",
      "div",
      "div"
    ],
    "click": [
      "div",
      "div",
      "div",
      "div"
    ],
    "the": [
      "div",
      "div",
      "div",
      "div",
      "div",
      "div",
      "div",
      "div",
      "div",
      "div",
      "div",
      "div",
      "div",
      "div"
    ],
    "link": [
      "div"
    ],
    "top": [
      "div"
    ],
    "right": [
      "div",
      "div",
      "div",
      "div"
    ],
    "of": [
      "div",
      "div"
    ],
    "main": [
      "div",
      "div"
    ],
    "interface": [
      "div",
      "div"
    ],
    "two": [
      "div"
    ],
    "ways": [
      "div"
    ],
    "folders": [
      "div",
      "div",
      "div",
      "title"
    ],
    "are": [
      "div"
    ],
    "context": [
      "div",
      "div"
    ],
    "menu": [
      "div",
      "div",
      "div"
    ],
    "drag": [
      "div",
      "div",
      "div",
      "div"
    ],
    "&": [
      "div",
      "div",
      "div"
    ],
    "drop": [
      "div",
      "div",
      "div"
    ],
    "operations": [
      "div",
      "div",
      "div",
      "div"
    ],
    "allow": [
      "div",
      "div",
      "div"
    ],
    "managing": [
      "div"
    ],
    "themselves": [
      "div"
    ],
    "while": [
      "div"
    ],
    "placing": [
      "div",
      "div"
    ],
    "inside": [
      "div",
      "div",
      "div"
    ],
    "provides": [
      "div"
    ],
    "following": [
      "div"
    ],
    "options": [
      "div"
    ],
    "add": [
      "div",
      "div",
      "div",
      "div"
    ],
    "view": [
      "div",
      "div",
      "div",
      "div"
    ],
    "folder": [
      "div",
      "div",
      "div",
      "div",
      "div",
      "div",
      "div",
      "div",
      "div",
      "div",
      "div",
      "div",
      "div",
      "div"
    ],
    "rename": [
      "div",
      "div"
    ],
    "delete": [
      "div",
      "div"
    ],
    "exit": [
      "div",
      "div"
    ],
    "creates": [
      "div",
      "div"
    ],
    "a": [
      "div",
      "div",
      "div",
      "div",
      "div"
    ],
    "new": [
      "div",
      "div"
    ],
    "selected": [
      "div",
      "div"
    ],
    "allows": [
      "div"
    ],
    "renaming": [
      "div"
    ],
    "current": [
      "div"
    ],
    "deletes": [
      "div"
    ],
    "clicked": [
      "div"
    ],
    "returns": [
      "div"
    ],
    "regular": [
      "div"
    ],
    "existing": [
      "div"
    ],
    "views": [
      "div"
    ],
    "move": [
      "div"
    ],
    "into": [
      "div",
      "div"
    ],
    "it": [
      "div"
    ],
    "destination": [
      "div"
    ]
  },
  "tags": {},
  "links": []
}