{
  "id": "00000000-0000-0000-0000-0000002ccdf6",
  "checksum": "02592f4853cee3c0274627487ec84a19",
  "words": {
    "36": [
      "p"
    ],
    "42": [
      "p",
      "p",
      "ul",
      "li",
      "ul",
      "li"
    ],
    "45": [
      "p"
    ],
    "46": [
      "ul",
      "li",
      "ul",
      "li"
    ],
    "64": [
      "ul",
      "li"
    ],
    "70": [
      "ul",
      "li",
      "ul",
      "li"
    ],
    "80": [
      "ul",
      "li"
    ],
    "100": [
      "p",
      "p"
    ],
    "451": [
      "ul",
      "li"
    ],
    "2012": [
      "ul",
      "li"
    ],
    "is": [
      "p",
      "p",
      "p",
      "p",
      "p",
      "p",
      "title"
    ],
    "building": [
      "p"
    ],
    "on": [
      "p",
      "p",
      "p",
      "ul",
      "li",
      "ul",
      "li"
    ],
    "top": [
      "p"
    ],
    "of": [
      "p",
      "p",
      "p",
      "p",
      "p",
      "p",
      "p",
      "ul",
      "ul",
      "li",
      "li"
    ],
    "success": [
      "p"
    ],
    "and": [
      "p",
      "p",
      "p",
      "p",
      "p",
      "p",
      "p",
      "p",
      "p",
      "ul",
      "ul",
      "li",
      "li",
      "p",
      "p",
      "ul",
      "li"
    ],
    "includes": [
      "p",
      "p"
    ],
    "": [
      "p",
      "p",
      "p",
      "p",
      "p",
      "p",
      "p",
      "p",
      "p",
      "p",
      "p",
      "p",
      "p",
      "p",
      "p",
      "p",
      "p",
      "p",
      "p",
      "p",
      "p",
      "p",
      "p",
      "p",
      "p",
      "p",
      "p",
      "p",
      "p",
      "p",
      "p",
      "p",
      "p",
      "p",
      "p",
      "p",
      "p",
      "p",
      "p",
      "p",
      "p",
      "p",
      "p",
      "p"
    ],
    "multiple": [
      "p",
      "p",
      "p"
    ],
    "search": [
      "p",
      "p"
    ],
    "improvements": [
      "p"
    ],
    "with": [
      "p",
      "p",
      "p",
      "p",
      "p",
      "ul",
      "li",
      "p"
    ],
    "more": [
      "p",
      "p"
    ],
    "relevant": [
      "p",
      "p",
      "p"
    ],
    "results": [
      "p",
      "p",
      "p"
    ],
    "updates": [
      "p"
    ],
    "to": [
      "p",
      "p",
      "p",
      "p",
      "p",
      "p",
      "p",
      "p",
      "p",
      "p",
      "p",
      "p"
    ],
    "latest": [
      "p"
    ],
    "stable": [
      "p"
    ],
    "versions": [
      "p"
    ],
    "underlying": [
      "p",
      "p"
    ],
    "nodejs": [
      "p"
    ],
    "components": [
      "p"
    ],
    "bug": [
      "p"
    ],
    "fixes": [
      "p"
    ],
    "over": [
      "p",
      "p"
    ],
    "additional": [
      "p",
      "p"
    ],
    "code": [
      "p",
      "p",
      "p",
      "p"
    ],
    "examples": [
      "p",
      "p"
    ],
    "linked": [
      "p"
    ],
    "guidelines": [
      "p"
    ],
    "how": [
      "p"
    ],
    "tos": [
      "p"
    ],
    "merged": [
      "p"
    ],
    "articles": [
      "p",
      "p",
      "p",
      "p"
    ],
    "general": [
      "p"
    ],
    "sweep": [
      "p"
    ],
    "for": [
      "p",
      "p",
      "p",
      "p",
      "p",
      "p",
      "ul",
      "li",
      "p"
    ],
    "outdated": [
      "p"
    ],
    "content": [
      "p",
      "p",
      "p",
      "p",
      "p"
    ],
    "a": [
      "p",
      "p",
      "p"
    ],
    "major": [
      "p",
      "p"
    ],
    "rewrite": [
      "p"
    ],
    "team": [
      "p",
      "p",
      "p"
    ],
    "mentor": [
      "p",
      "p",
      "p"
    ],
    "under": [
      "p",
      "p"
    ],
    "new": [
      "p",
      "p",
      "title"
    ],
    "architecture": [
      "p"
    ],
    "this": [
      "p",
      "ul",
      "li",
      "title"
    ],
    "simplified": [
      "p"
    ],
    "modern": [
      "p"
    ],
    "easy": [
      "p",
      "p",
      "p"
    ],
    "use": [
      "p",
      "p"
    ],
    "interface": [
      "p"
    ],
    "intuitive": [
      "p",
      "p"
    ],
    "design": [
      "p"
    ],
    "focus": [
      "p"
    ],
    "making": [
      "p",
      "p"
    ],
    "it": [
      "p",
      "p",
      "p"
    ],
    "find": [
      "p",
      "p"
    ],
    "answers": [
      "p"
    ],
    "security": [
      "p"
    ],
    "questions": [
      "p"
    ],
    "improved": [
      "p",
      "p"
    ],
    "filter": [
      "p"
    ],
    "capability": [
      "p"
    ],
    "algorithmically": [
      "p"
    ],
    "presents": [
      "p"
    ],
    "the": [
      "p",
      "p",
      "p",
      "p",
      "p",
      "p"
    ],
    "most": [
      "p"
    ],
    "allows": [
      "p"
    ],
    "further": [
      "p"
    ],
    "narrow": [
      "p"
    ],
    "down": [
      "p",
      "p"
    ],
    "robust": [
      "p",
      "p"
    ],
    "filtering": [
      "p"
    ],
    "ability": [
      "p"
    ],
    "browse": [
      "p",
      "p"
    ],
    "users": [
      "p"
    ],
    "can": [
      "p",
      "ul",
      "li"
    ],
    "now": [
      "p",
      "p"
    ],
    "by": [
      "p"
    ],
    "subject": [
      "p",
      "p"
    ],
    "matter": [
      "p",
      "p"
    ],
    "technology": [
      "p"
    ],
    "article": [
      "p",
      "p"
    ],
    "type": [
      "p"
    ],
    "other": [
      "p"
    ],
    "keywords": [
      "p"
    ],
    "progressively": [
      "p"
    ],
    "narrowing": [
      "p"
    ],
    "selected": [
      "p"
    ],
    "filters": [
      "p",
      "p"
    ],
    "main": [
      "p",
      "p",
      "p"
    ],
    "user": [
      "p",
      "p"
    ],
    "ui": [
      "p",
      "p"
    ],
    "fully": [
      "p"
    ],
    "written": [
      "p"
    ],
    "in": [
      "p",
      "p",
      "p",
      "title"
    ],
    "node": [
      "p"
    ],
    "js": [
      "p"
    ],
    "support": [
      "p",
      "ul",
      "li"
    ],
    "all": [
      "p",
      "p",
      "p"
    ],
    "browsers": [
      "p",
      "p",
      "ul",
      "li",
      "p",
      "p"
    ],
    "including": [
      "p",
      "p"
    ],
    "legacy": [
      "p"
    ],
    "mobile": [
      "p",
      "ul",
      "li"
    ],
    "nosql": [
      "p"
    ],
    "database": [
      "p"
    ],
    "integration": [
      "p",
      "p"
    ],
    "current": [
      "p"
    ],
    "editor": [
      "p"
    ],
    "admin": [
      "p"
    ],
    "interfaces": [
      "p"
    ],
    "piwik": [
      "p"
    ],
    "statistical": [
      "p"
    ],
    "information": [
      "p",
      "p",
      "p"
    ],
    "had": [
      "p"
    ],
    "been": [
      "p"
    ],
    "re": [
      "p"
    ],
    "classified": [
      "p"
    ],
    "into": [
      "p"
    ],
    "areas": [
      "p"
    ],
    "browsing": [
      "p"
    ],
    "through": [
      "p"
    ],
    "taxonomy": [
      "p"
    ],
    "appropriately": [
      "p"
    ],
    "changed": [
      "p"
    ],
    "clean": [
      "p"
    ],
    "up": [
      "p"
    ],
    "removal": [
      "p"
    ],
    "too": [
      "p"
    ],
    "little": [
      "p"
    ],
    "moved": [
      "p"
    ],
    "away": [
      "p"
    ],
    "from": [
      "p",
      "ul",
      "li"
    ],
    "library": [
      "p",
      "p"
    ],
    "structure": [
      "p"
    ],
    "one": [
      "p"
    ],
    "well": [
      "p"
    ],
    "organized": [
      "p"
    ],
    "aws": [
      "p"
    ],
    "minimum": [
      "p",
      "p"
    ],
    "requirements": [
      "p",
      "p",
      "p",
      "p"
    ],
    "note": [
      "p",
      "p",
      "p"
    ],
    "change": [
      "p"
    ],
    "specified": [
      "p"
    ],
    "here": [
      "p"
    ],
    "server": [
      "p"
    ],
    "side": [
      "p",
      "p",
      "p"
    ],
    "windows": [
      "ul",
      "li"
    ],
    "r2": [
      "ul",
      "li"
    ],
    "bit": [
      "ul",
      "li"
    ],
    "iis": [
      "ul",
      "li"
    ],
    "or": [
      "ul",
      "li",
      "ul",
      "ul",
      "ul",
      "li",
      "li",
      "li",
      "ul",
      "ul",
      "ul",
      "li",
      "li",
      "li"
    ],
    "higher": [
      "ul",
      "li",
      "ul",
      "ul",
      "ul",
      "li",
      "li",
      "li",
      "ul",
      "ul",
      "ul",
      "li",
      "li",
      "li"
    ],
    "net": [
      "ul",
      "li"
    ],
    "framework": [
      "ul",
      "li"
    ],
    "you": [
      "ul",
      "li"
    ],
    "download": [
      "ul",
      "li"
    ],
    "version": [
      "ul",
      "li",
      "p",
      "p"
    ],
    "http//wwwmicrosoftcom/en": [
      "ul",
      "li",
      "a"
    ],
    "us/download/detailsaspx?id=40779": [
      "ul",
      "li",
      "a"
    ],
    "4gb": [
      "ul",
      "ul",
      "li",
      "li"
    ],
    "ram": [
      "ul",
      "li",
      "p"
    ],
    "storage": [
      "ul",
      "li",
      "p"
    ],
    "ssl": [
      "ul",
      "li",
      "p"
    ],
    "certificate": [
      "ul",
      "li",
      "p",
      "p"
    ],
    "please": [
      "p"
    ],
    "that": [
      "p"
    ],
    "may": [
      "p",
      "p"
    ],
    "be": [
      "p",
      "p"
    ],
    "possible": [
      "p"
    ],
    "run": [
      "p"
    ],
    "less": [
      "p"
    ],
    "however": [
      "p"
    ],
    "performance": [
      "p"
    ],
    "does": [
      "p"
    ],
    "degrade": [
      "p"
    ],
    "load": [
      "p"
    ],
    "minimal": [
      "p"
    ],
    "configuration": [
      "p"
    ],
    "listed": [
      "p"
    ],
    "above": [
      "p"
    ],
    "recommended": [
      "p"
    ],
    "production": [
      "p"
    ],
    "environments": [
      "p",
      "p"
    ],
    "also": [
      "p"
    ],
    "when": [
      "p"
    ],
    "connecting": [
      "p",
      "p"
    ],
    "local": [
      "p"
    ],
    "machine": [
      "p"
    ],
    "localhost": [
      "p"
    ],
    "not": [
      "p"
    ],
    "required": [
      "p"
    ],
    "self": [
      "p"
    ],
    "signed": [
      "p"
    ],
    "used": [
      "p",
      "p"
    ],
    "test": [
      "p"
    ],
    "client": [
      "p",
      "p"
    ],
    "named": [
      "p",
      "p"
    ],
    "flare": [
      "p"
    ],
    "requires": [
      "p"
    ],
    "ie11": [
      "ul",
      "li",
      "ul",
      "li"
    ],
    "firefox": [
      "ul",
      "li",
      "ul",
      "li"
    ],
    "chrome": [
      "ul",
      "li",
      "ul",
      "li"
    ],
    "safari": [
      "ul",
      "li",
      "ul",
      "li"
    ],
    "v61": [
      "ul",
      "li",
      "ul",
      "li"
    ],
    "osx": [
      "ul",
      "li",
      "ul",
      "li"
    ],
    "only": [
      "ul",
      "li",
      "ul",
      "li"
    ],
    "android": [
      "ul",
      "li"
    ],
    "ios": [
      "ul",
      "li"
    ],
    "have": [
      "ul",
      "li"
    ],
    "experimental": [
      "ul",
      "li"
    ],
    "there": [
      "p"
    ],
    "fallback": [
      "p"
    ],
    "jade": [
      "p",
      "p"
    ],
    "supports": [
      "p",
      "p"
    ],
    "available": [
      "p"
    ],
    "ie8": [
      "p"
    ],
    "lynx": [
      "p"
    ],
    "tm": [
      "p"
    ],
    "back": [
      "p"
    ],
    "end": [
      "p"
    ],
    "administration": [
      "p"
    ],
    "editing": [
      "p"
    ],
    "following": [
      "p"
    ],
    "what": [
      "title"
    ],
    "release?": [
      "title"
    ]
  },
  "tags": {},
  "links": [
    {
      "href": "http://www.microsoft.com/en-us/download/details.aspx?id=40779",
      "text": "http://www.microsoft.com/en-us/download/details.aspx?id=40779"
    }
  ]
}